count_lines/__init__.py
count_lines/cli.py
count_lines-0.1.1.dist-info/entry_points.txt
count_lines-0.1.1.dist-info/WHEEL
count_lines-0.1.1.dist-info/METADATA
count_lines-0.1.1.dist-info/RECORD
