Metadata-Version: 2.1
Name: count-lines
Version: 0.1.1
Summary: 
Home-page: https://github.com/eyalev/count-lines
Author: Eyal Levin
Author-email: eyalev@gmail.com
Requires-Python: >=3.6,<4.0
Classifier: Programming Language :: Python :: 3
Classifier: Programming Language :: Python :: 3.6
Classifier: Programming Language :: Python :: 3.7
Classifier: Programming Language :: Python :: 3.8
Requires-Dist: click (>=7.1.2,<8.0.0)
Requires-Dist: clipboard-util (>=0.1.1,<0.2.0)
Requires-Dist: input-util (>=0.1.1,<0.2.0)
Project-URL: Repository, https://github.com/eyalev/count-lines
